{
  "name": "Don Siegel",
  "slug": "don-siegel",
  "titles": [
    {
      "creditedAs": [
        "director"
      ],
      "imdbId": "tt0041178",
      "title": "The Big Steal",
      "year": "1949",
      "slug": "the-big-steal-1949",
      "grade": "B-",
      "sortTitle": "big-steal-1949",
      "gradeValue": 8,
      "releaseSequence": "1949-06-29tt0041178",
      "reviewDate": "2022-10-20",
      "reviewSequence": "2022-10-20-1",
      "watchlistDirectorNames": [],
      "watchlistPerformerNames": [],
      "watchlistWriterNames": [],
      "collectionNames": []
    },
    {
      "creditedAs": [
        "director"
      ],
      "imdbId": "tt0044573",
      "title": "The Duel at Silver Creek",
      "year": "1952",
      "slug": "the-duel-at-silver-creek-1952",
      "grade": "D",
      "sortTitle": "duel-at-silver-creek-1952",
      "gradeValue": 3,
      "releaseSequence": "1952-08-01tt0044573",
      "reviewDate": "2023-03-23",
      "reviewSequence": "2023-03-23-1",
      "watchlistDirectorNames": [],
      "watchlistPerformerNames": [],
      "watchlistWriterNames": [],
      "collectionNames": []
    },
    {
      "creditedAs": [
        "director"
      ],
      "imdbId": "tt0056062",
      "title": "Hell Is for Heroes",
      "year": "1962",
      "slug": "hell-is-for-heroes-1962",
      "grade": "B",
      "sortTitle": "hell-is-for-heroes-1962",
      "gradeValue": 9,
      "releaseSequence": "1962-??-??tt0056062",
      "reviewDate": "2015-07-11",
      "reviewSequence": "2015-07-11-1",
      "watchlistDirectorNames": [],
      "watchlistPerformerNames": [],
      "watchlistWriterNames": [],
      "collectionNames": []
    },
    {
      "creditedAs": [
        "director"
      ],
      "imdbId": "tt0058262",
      "title": "The Killers",
      "year": "1964",
      "slug": null,
      "grade": null,
      "sortTitle": "killers-1964",
      "gradeValue": null,
      "releaseSequence": "1964-07-07tt0058262",
      "reviewDate": null,
      "reviewSequence": null,
      "watchlistDirectorNames": [],
      "watchlistPerformerNames": [
        "Lee Marvin"
      ],
      "watchlistWriterNames": [],
      "collectionNames": []
    },
    {
      "creditedAs": [
        "director"
      ],
      "imdbId": "tt0075213",
      "title": "The Shootist",
      "year": "1976",
      "slug": "the-shootist-1976",
      "grade": "B+",
      "sortTitle": "shootist-1976",
      "gradeValue": 10,
      "releaseSequence": "1976-07-16tt0075213",
      "reviewDate": "2008-01-21",
      "reviewSequence": "2008-01-21-1",
      "watchlistDirectorNames": [],
      "watchlistPerformerNames": [],
      "watchlistWriterNames": [],
      "collectionNames": []
    },
    {
      "creditedAs": [
        "performer"
      ],
      "imdbId": "tt0077745",
      "title": "Invasion of the Body Snatchers",
      "year": "1978",
      "slug": "invasion-of-the-body-snatchers-1978",
      "grade": "B",
      "sortTitle": "invasion-of-the-body-snatchers-1978",
      "gradeValue": 9,
      "releaseSequence": "1978-12-21tt0077745",
      "reviewDate": "2007-09-29",
      "reviewSequence": "2007-09-29-1",
      "watchlistDirectorNames": [],
      "watchlistPerformerNames": [],
      "watchlistWriterNames": [],
      "collectionNames": []
    },
    {
      "creditedAs": [
        "director"
      ],
      "imdbId": "tt0079116",
      "title": "Escape from Alcatraz",
      "year": "1979",
      "slug": "escape-from-alcatraz-1979",
      "grade": "B",
      "sortTitle": "escape-from-alcatraz-1979",
      "gradeValue": 9,
      "releaseSequence": "1979-06-22tt0079116",
      "reviewDate": "2025-06-03",
      "reviewSequence": "2025-06-03-1",
      "watchlistDirectorNames": [],
      "watchlistPerformerNames": [],
      "watchlistWriterNames": [],
      "collectionNames": []
    }
  ],
  "reviewCount": 6,
  "totalCount": 7,
  "creditedAs": [
    "director",
    "performer"
  ]
}