[
  {
    "imdbId": "tt14549466",
    "title": "Crimes of the Future",
    "year": "2022",
    "sortTitle": "Crimes of the Future (2022)",
    "slug": "crimes-of-the-future-2022",
    "grade": "B-",
    "gradeValue": 8,
    "genres": [
      "Drama",
      "Horror",
      "Sci-Fi"
    ],
    "releaseSequence": "2022-05-23tt14549466"
  },
  {
    "imdbId": "tt0293429",
    "title": "Mortal Kombat",
    "year": "2021",
    "sortTitle": "Mortal Kombat (2021)",
    "slug": "mortal-kombat-2021",
    "grade": "B-",
    "gradeValue": 8,
    "genres": [
      "Action",
      "Adventure",
      "Fantasy",
      "Sci-Fi",
      "Thriller"
    ],
    "releaseSequence": "2021-04-01tt0293429"
  },
  {
    "imdbId": "tt11252440",
    "title": "Psycho Goreman",
    "year": "2020",
    "sortTitle": "Psycho Goreman (2020)",
    "slug": "psycho-goreman-2020",
    "grade": "B",
    "gradeValue": 9,
    "genres": [
      "Comedy",
      "Horror",
      "Sci-Fi"
    ],
    "releaseSequence": "2020-09-10tt11252440"
  },
  {
    "imdbId": "tt5073642",
    "title": "Color Out of Space",
    "year": "2019",
    "sortTitle": "Color Out of Space (2019)",
    "slug": "color-out-of-space-2019",
    "grade": "B-",
    "gradeValue": 8,
    "genres": [
      "Horror",
      "Mystery",
      "Sci-Fi",
      "Thriller"
    ],
    "releaseSequence": "2019-09-07tt5073642"
  },
  {
    "imdbId": "tt7772580",
    "title": "The Perfection",
    "year": "2018",
    "sortTitle": "Perfection (2018)",
    "slug": "the-perfection-2018",
    "grade": "B-",
    "gradeValue": 8,
    "genres": [
      "Drama",
      "Horror",
      "Music",
      "Thriller"
    ],
    "releaseSequence": "2018-09-20tt7772580"
  },
  {
    "imdbId": "tt7464188",
    "title": "In Fabric",
    "year": "2018",
    "sortTitle": "In Fabric (2018)",
    "slug": "in-fabric-2018",
    "grade": "B",
    "gradeValue": 9,
    "genres": [
      "Comedy",
      "Drama",
      "Fantasy",
      "Horror",
      "Mystery",
      "Thriller"
    ],
    "releaseSequence": "2018-09-13tt7464188"
  },
  {
    "imdbId": "tt6516314",
    "title": "Piercing",
    "year": "2018",
    "sortTitle": "Piercing (2018)",
    "slug": "piercing-2018",
    "grade": "B",
    "gradeValue": 9,
    "genres": [
      "Horror",
      "Mystery",
      "Thriller"
    ],
    "releaseSequence": "2018-01-20tt6516314"
  },
  {
    "imdbId": "tt4381236",
    "title": "The Greasy Strangler",
    "year": "2016",
    "sortTitle": "Greasy Strangler (2016)",
    "slug": "the-greasy-strangler-2016",
    "grade": "A-",
    "gradeValue": 11,
    "genres": [
      "Comedy",
      "Horror"
    ],
    "releaseSequence": "2016-01-22tt4381236"
  },
  {
    "imdbId": "tt3850590",
    "title": "Krampus",
    "year": "2015",
    "sortTitle": "Krampus (2015)",
    "slug": "krampus-2015",
    "grade": "B-",
    "gradeValue": 8,
    "genres": [
      "Comedy",
      "Fantasy",
      "Horror"
    ],
    "releaseSequence": "2015-11-30tt3850590"
  },
  {
    "imdbId": "tt2781516",
    "title": "Wolfcop",
    "year": "2014",
    "sortTitle": "Wolfcop (2014)",
    "slug": "wolfcop-2014",
    "grade": "B",
    "gradeValue": 9,
    "genres": [
      "Comedy",
      "Horror"
    ],
    "releaseSequence": "2014-06-06tt2781516"
  },
  {
    "imdbId": "tt1441395",
    "title": "Under the Skin",
    "year": "2013",
    "sortTitle": "Under the Skin (2013)",
    "slug": "under-the-skin-2013",
    "grade": "B-",
    "gradeValue": 8,
    "genres": [
      "Drama",
      "Horror",
      "Mystery",
      "Sci-Fi",
      "Thriller"
    ],
    "releaseSequence": "2013-08-29tt1441395"
  },
  {
    "imdbId": "tt1977895",
    "title": "Resolution",
    "year": "2012",
    "sortTitle": "Resolution (2012)",
    "slug": "resolution-2012",
    "grade": "B+",
    "gradeValue": 10,
    "genres": [
      "Drama",
      "Horror",
      "Mystery",
      "Sci-Fi",
      "Thriller"
    ],
    "releaseSequence": "2012-04-22tt1977895"
  },
  {
    "imdbId": "tt1788391",
    "title": "Kill List",
    "year": "2011",
    "sortTitle": "Kill List (2011)",
    "slug": "kill-list-2011",
    "grade": "B+",
    "gradeValue": 10,
    "genres": [
      "Crime",
      "Drama",
      "Horror",
      "Mystery",
      "Thriller"
    ],
    "releaseSequence": "2011-03-12tt1788391"
  },
  {
    "imdbId": "tt1489167",
    "title": "Down Terrace",
    "year": "2009",
    "sortTitle": "Down Terrace (2009)",
    "slug": "down-terrace-2009",
    "grade": "B-",
    "gradeValue": 8,
    "genres": [
      "Comedy",
      "Crime",
      "Drama"
    ],
    "releaseSequence": "2009-09-01tt1489167"
  },
  {
    "imdbId": "tt1278340",
    "title": "Dead Snow",
    "year": "2009",
    "sortTitle": "Dead Snow (2009)",
    "slug": "dead-snow-2009",
    "grade": "B+",
    "gradeValue": 10,
    "genres": [
      "Comedy",
      "Fantasy",
      "Horror"
    ],
    "releaseSequence": "2009-01-09tt1278340"
  },
  {
    "imdbId": "tt1121931",
    "title": "Crank: High Voltage",
    "year": "2009",
    "sortTitle": "Crank: High Voltage (2009)",
    "slug": "crank-high-voltage-2009",
    "grade": "A-",
    "gradeValue": 11,
    "genres": [
      "Action",
      "Thriller"
    ],
    "releaseSequence": "2009-04-16tt1121931"
  },
  {
    "imdbId": "tt1001508",
    "title": "He's Just Not That Into You",
    "year": "2009",
    "sortTitle": "He's Just Not That Into You (2009)",
    "slug": "hes-just-not-that-into-you-2009",
    "grade": "B-",
    "gradeValue": 8,
    "genres": [
      "Comedy",
      "Drama",
      "Romance"
    ],
    "releaseSequence": "2009-01-24tt1001508"
  },
  {
    "imdbId": "tt0839980",
    "title": "Semi-Pro",
    "year": "2008",
    "sortTitle": "Semi-Pro (2008)",
    "slug": "semi-pro-2008",
    "grade": "B-",
    "gradeValue": 8,
    "genres": [
      "Comedy",
      "Sport"
    ],
    "releaseSequence": "2008-02-19tt0839980"
  },
  {
    "imdbId": "tt0452702",
    "title": "Vacancy",
    "year": "2007",
    "sortTitle": "Vacancy (2007)",
    "slug": "vacancy-2007",
    "grade": "B-",
    "gradeValue": 8,
    "genres": [
      "Horror",
      "Thriller"
    ],
    "releaseSequence": "2007-04-20tt0452702"
  },
  {
    "imdbId": "tt0442933",
    "title": "Beowulf",
    "year": "2007",
    "sortTitle": "Beowulf (2007)",
    "slug": "beowulf-2007",
    "grade": "B+",
    "gradeValue": 10,
    "genres": [
      "Animation",
      "Action",
      "Adventure",
      "Fantasy"
    ],
    "releaseSequence": "2007-11-05tt0442933"
  },
  {
    "imdbId": "tt0486551",
    "title": "Beerfest",
    "year": "2006",
    "sortTitle": "Beerfest (2006)",
    "slug": "beerfest-2006",
    "grade": "A-",
    "gradeValue": 11,
    "genres": [
      "Comedy"
    ],
    "releaseSequence": "2006-08-25tt0486551"
  },
  {
    "imdbId": "tt0264508",
    "title": "Dagon",
    "year": "2001",
    "sortTitle": "Dagon (2001)",
    "slug": "dagon-2001",
    "grade": "B",
    "gradeValue": 9,
    "genres": [
      "Fantasy",
      "Horror",
      "Mystery"
    ],
    "releaseSequence": "2001-10-12tt0264508"
  },
  {
    "imdbId": "tt0275773",
    "title": "Versus",
    "year": "2000",
    "sortTitle": "Versus (2000)",
    "slug": "versus-2000",
    "grade": "B-",
    "gradeValue": 8,
    "genres": [
      "Action",
      "Drama",
      "Fantasy",
      "Horror",
      "Thriller"
    ],
    "releaseSequence": "2000-10-29tt0275773"
  },
  {
    "imdbId": "tt0110823",
    "title": "Phantasm III: Lord of the Dead",
    "year": "1994",
    "sortTitle": "Phantasm III: Lord of the Dead (1994)",
    "slug": "phantasm-iii-lord-of-the-dead-1994",
    "grade": "B-",
    "gradeValue": 8,
    "genres": [
      "Action",
      "Fantasy",
      "Horror",
      "Sci-Fi"
    ],
    "releaseSequence": "1994-02-25tt0110823"
  },
  {
    "imdbId": "tt0106215",
    "title": "Mutant Action",
    "year": "1993",
    "sortTitle": "Mutant Action (1993)",
    "slug": "mutant-action-1993",
    "grade": "B-",
    "gradeValue": 8,
    "genres": [
      "Comedy",
      "Fantasy",
      "Sci-Fi",
      "Thriller"
    ],
    "releaseSequence": "1993-01-18tt0106215"
  },
  {
    "imdbId": "tt0099611",
    "title": "Frankenhooker",
    "year": "1990",
    "sortTitle": "Frankenhooker (1990)",
    "slug": "frankenhooker-1990",
    "grade": "B-",
    "gradeValue": 8,
    "genres": [
      "Comedy",
      "Horror",
      "Sci-Fi"
    ],
    "releaseSequence": "1990-04-01tt0099611"
  },
  {
    "imdbId": "tt0096920",
    "title": "Beyond the Door III",
    "year": "1989",
    "sortTitle": "Beyond the Door III (1989)",
    "slug": "beyond-the-door-iii-1989",
    "grade": "B-",
    "gradeValue": 8,
    "genres": [
      "Drama",
      "Fantasy",
      "Horror"
    ],
    "releaseSequence": "1989-10-01tt0096920"
  },
  {
    "imdbId": "tt0093912",
    "title": "Salvation!",
    "year": "1987",
    "sortTitle": "Salvation! (1987)",
    "slug": "salvation-have-you-said-your-prayers-today-1987",
    "grade": "B",
    "gradeValue": 9,
    "genres": [
      "Comedy"
    ],
    "releaseSequence": "1987-05-31tt0093912"
  },
  {
    "imdbId": "tt0091990",
    "title": "Sorority House Massacre",
    "year": "1986",
    "sortTitle": "Sorority House Massacre (1986)",
    "slug": "sorority-house-massacre-1986",
    "grade": "B-",
    "gradeValue": 8,
    "genres": [
      "Horror"
    ],
    "releaseSequence": "1986-10-10tt0091990"
  },
  {
    "imdbId": "tt0091080",
    "title": "Friday the 13th Part VI: Jason Lives",
    "year": "1986",
    "sortTitle": "Friday the 13th Part VI: Jason Lives (1986)",
    "slug": "friday-the-13th-part-vi-jason-lives-1986",
    "grade": "B-",
    "gradeValue": 8,
    "genres": [
      "Horror",
      "Thriller"
    ],
    "releaseSequence": "1986-08-01tt0091080"
  },
  {
    "imdbId": "tt0089789",
    "title": "The Peanut Butter Solution",
    "year": "1985",
    "sortTitle": "Peanut Butter Solution (1985)",
    "slug": "the-peanut-butter-solution-1985",
    "grade": "B-",
    "gradeValue": 8,
    "genres": [
      "Adventure",
      "Comedy",
      "Family",
      "Fantasy",
      "Horror"
    ],
    "releaseSequence": "1985-12-04tt0089789"
  },
  {
    "imdbId": "tt0088708",
    "title": "American Ninja",
    "year": "1985",
    "sortTitle": "American Ninja (1985)",
    "slug": "american-ninja-1985",
    "grade": "B-",
    "gradeValue": 8,
    "genres": [
      "Action",
      "Adventure",
      "Romance"
    ],
    "releaseSequence": "1985-08-30tt0088708"
  },
  {
    "imdbId": "tt0087298",
    "title": "Friday the 13th: The Final Chapter",
    "year": "1984",
    "sortTitle": "Friday the 13th: The Final Chapter (1984)",
    "slug": "friday-the-13th-the-final-chapter-1984",
    "grade": "B",
    "gradeValue": 9,
    "genres": [
      "Horror",
      "Thriller"
    ],
    "releaseSequence": "1984-04-13tt0087298"
  },
  {
    "imdbId": "tt0084719",
    "title": "The New York Ripper",
    "year": "1982",
    "sortTitle": "New York Ripper (1982)",
    "slug": "the-new-york-ripper-1982",
    "grade": "B-",
    "gradeValue": 8,
    "genres": [
      "Horror",
      "Mystery",
      "Thriller"
    ],
    "releaseSequence": "1982-03-04tt0084719"
  },
  {
    "imdbId": "tt0082782",
    "title": "My Bloody Valentine",
    "year": "1981",
    "sortTitle": "My Bloody Valentine (1981)",
    "slug": "my-bloody-valentine-1981",
    "grade": "B-",
    "gradeValue": 8,
    "genres": [
      "Horror",
      "Mystery",
      "Thriller"
    ],
    "releaseSequence": "1981-02-11tt0082782"
  },
  {
    "imdbId": "tt0081793",
    "title": "Christmas Evil",
    "year": "1980",
    "sortTitle": "Christmas Evil (1980)",
    "slug": "christmas-evil-1980",
    "grade": "B+",
    "gradeValue": 10,
    "genres": [
      "Horror",
      "Thriller"
    ],
    "releaseSequence": "1980-11-01tt0081793"
  },
  {
    "imdbId": "tt0081318",
    "title": "City of the Living Dead",
    "year": "1980",
    "sortTitle": "City of the Living Dead (1980)",
    "slug": "city-of-the-living-dead-1980",
    "grade": "B+",
    "gradeValue": 10,
    "genres": [
      "Horror"
    ],
    "releaseSequence": "1980-08-11tt0081318"
  },
  {
    "imdbId": "tt0080904",
    "title": "Humanoids from the Deep",
    "year": "1980",
    "sortTitle": "Humanoids from the Deep (1980)",
    "slug": "humanoids-from-the-deep-1980",
    "grade": "B-",
    "gradeValue": 8,
    "genres": [
      "Horror",
      "Sci-Fi"
    ],
    "releaseSequence": "1980-03-28tt0080904"
  },
  {
    "imdbId": "tt0080354",
    "title": "Alligator",
    "year": "1980",
    "sortTitle": "Alligator (1980)",
    "slug": "alligator-1980",
    "grade": "B",
    "gradeValue": 9,
    "genres": [
      "Horror",
      "Sci-Fi",
      "Thriller"
    ],
    "releaseSequence": "1980-11-14tt0080354"
  },
  {
    "imdbId": "tt0079082",
    "title": "The Driller Killer",
    "year": "1979",
    "sortTitle": "Driller Killer (1979)",
    "slug": "the-driller-killer-1979",
    "grade": "B-",
    "gradeValue": 8,
    "genres": [
      "Drama",
      "Horror",
      "Thriller"
    ],
    "releaseSequence": "1979-06-15tt0079082"
  },
  {
    "imdbId": "tt0074510",
    "title": "Scalpel",
    "year": "1977",
    "sortTitle": "Scalpel (1977)",
    "slug": "scalpel-1977",
    "grade": "B-",
    "gradeValue": 8,
    "genres": [
      "Drama",
      "Horror",
      "Thriller"
    ],
    "releaseSequence": "1977-01-01tt0074510"
  },
  {
    "imdbId": "tt0188527",
    "title": "Island of Death",
    "year": "1976",
    "sortTitle": "Island of Death (1976)",
    "slug": "island-of-death-1976",
    "grade": "B",
    "gradeValue": 9,
    "genres": [
      "Horror",
      "Romance"
    ],
    "releaseSequence": "1976-??-??tt0188527"
  },
  {
    "imdbId": "tt0073836",
    "title": "Last Stop on the Night Train",
    "year": "1975",
    "sortTitle": "Last Stop on the Night Train (1975)",
    "slug": "last-stop-on-the-night-train-1975",
    "grade": "B-",
    "gradeValue": 8,
    "genres": [
      "Horror",
      "Thriller"
    ],
    "releaseSequence": "1975-04-08tt0073836"
  },
  {
    "imdbId": "tt0073735",
    "title": "Welcome Home Brother Charles",
    "year": "1975",
    "sortTitle": "Welcome Home Brother Charles (1975)",
    "slug": "welcome-home-brother-charles-1975",
    "grade": "B-",
    "gradeValue": 8,
    "genres": [
      "Action",
      "Drama",
      "Horror"
    ],
    "releaseSequence": "1975-11-21tt0073735"
  },
  {
    "imdbId": "tt0072285",
    "title": "Thriller: A Cruel Picture",
    "year": "1973",
    "sortTitle": "Thriller: A Cruel Picture (1973)",
    "slug": "thriller-a-cruel-picture-1973",
    "grade": "B-",
    "gradeValue": 8,
    "genres": [
      "Action",
      "Crime",
      "Drama",
      "Horror",
      "Thriller"
    ],
    "releaseSequence": "1973-05-01tt0072285"
  },
  {
    "imdbId": "tt0070794",
    "title": "The Thief Who Came to Dinner",
    "year": "1973",
    "sortTitle": "Thief Who Came to Dinner (1973)",
    "slug": "the-thief-who-came-to-dinner-1973",
    "grade": "B+",
    "gradeValue": 10,
    "genres": [
      "Comedy",
      "Romance"
    ],
    "releaseSequence": "1973-03-01tt0070794"
  },
  {
    "imdbId": "tt0068337",
    "title": "The Carey Treatment",
    "year": "1972",
    "sortTitle": "Carey Treatment (1972)",
    "slug": "the-carey-treatment-1972",
    "grade": "B-",
    "gradeValue": 8,
    "genres": [
      "Crime",
      "Mystery",
      "Thriller"
    ],
    "releaseSequence": "1972-03-29tt0068337"
  },
  {
    "imdbId": "tt0068675",
    "title": "Hannie Caulder",
    "year": "1971",
    "sortTitle": "Hannie Caulder (1971)",
    "slug": "hannie-caulder-1971",
    "grade": "B",
    "gradeValue": 9,
    "genres": [
      "Crime",
      "Drama",
      "Western"
    ],
    "releaseSequence": "1971-11-08tt0068675"
  },
  {
    "imdbId": "tt0066767",
    "title": "The Anderson Tapes",
    "year": "1971",
    "sortTitle": "Anderson Tapes (1971)",
    "slug": "the-anderson-tapes-1971",
    "grade": "B-",
    "gradeValue": 8,
    "genres": [
      "Action",
      "Crime",
      "Thriller"
    ],
    "releaseSequence": "1971-06-17tt0066767"
  },
  {
    "imdbId": "tt0066952",
    "title": "Count Yorga, Vampire",
    "year": "1970",
    "sortTitle": "Count Yorga, Vampire (1970)",
    "slug": "count-yorga-vampire-1970",
    "grade": "B",
    "gradeValue": 9,
    "genres": [
      "Drama",
      "Fantasy",
      "Horror",
      "Mystery",
      "Romance",
      "Thriller"
    ],
    "releaseSequence": "1970-06-10tt0066952"
  },
  {
    "imdbId": "tt0065466",
    "title": "Beyond the Valley of the Dolls",
    "year": "1970",
    "sortTitle": "Beyond the Valley of the Dolls (1970)",
    "slug": "beyond-the-valley-of-the-dolls-1970",
    "grade": "B-",
    "gradeValue": 8,
    "genres": [
      "Comedy",
      "Drama",
      "Music"
    ],
    "releaseSequence": "1970-06-17tt0065466"
  },
  {
    "imdbId": "tt0064949",
    "title": "Scream and Scream Again",
    "year": "1970",
    "sortTitle": "Scream and Scream Again (1970)",
    "slug": "scream-and-scream-again-1970",
    "grade": "B-",
    "gradeValue": 8,
    "genres": [
      "Crime",
      "Drama",
      "Horror",
      "Mystery",
      "Sci-Fi",
      "Thriller"
    ],
    "releaseSequence": "1970-01-01tt0064949"
  },
  {
    "imdbId": "tt0163114",
    "title": "Murder \u00e0 la Mod",
    "year": "1968",
    "sortTitle": "Murder \u00e0 la Mod (1968)",
    "slug": "murder-a-la-mod-1968",
    "grade": "B-",
    "gradeValue": 8,
    "genres": [
      "Comedy",
      "Crime",
      "Mystery",
      "Thriller"
    ],
    "releaseSequence": "1968-05-01tt0163114"
  },
  {
    "imdbId": "tt0060548",
    "title": "Island of Terror",
    "year": "1966",
    "sortTitle": "Island of Terror (1966)",
    "slug": "island-of-terror-1966",
    "grade": "B-",
    "gradeValue": 8,
    "genres": [
      "Horror",
      "Sci-Fi"
    ],
    "releaseSequence": "1966-06-03tt0060548"
  },
  {
    "imdbId": "tt0059258",
    "title": "Having a Wild Weekend",
    "year": "1965",
    "sortTitle": "Having a Wild Weekend (1965)",
    "slug": "having-a-wild-weekend-1965",
    "grade": "B-",
    "gradeValue": 8,
    "genres": [
      "Comedy",
      "Music"
    ],
    "releaseSequence": "1965-07-15tt0059258"
  },
  {
    "imdbId": "tt0056347",
    "title": "The Phantom of the Opera",
    "year": "1962",
    "sortTitle": "Phantom of the Opera (1962)",
    "slug": "the-phantom-of-the-opera-1962",
    "grade": "B",
    "gradeValue": 9,
    "genres": [
      "Drama",
      "Horror",
      "Music",
      "Mystery",
      "Romance",
      "Thriller"
    ],
    "releaseSequence": "1962-??-??tt0056347"
  },
  {
    "imdbId": "tt0054346",
    "title": "The Stranglers of Bombay",
    "year": "1959",
    "sortTitle": "Stranglers of Bombay (1959)",
    "slug": "the-stranglers-of-bombay-1959",
    "grade": "B",
    "gradeValue": 9,
    "genres": [
      "Action",
      "Adventure",
      "History",
      "Horror"
    ],
    "releaseSequence": "1959-12-04tt0054346"
  },
  {
    "imdbId": "tt0048983",
    "title": "Bandido!",
    "year": "1956",
    "sortTitle": "Bandido! (1956)",
    "slug": "bandido-1956",
    "grade": "B-",
    "gradeValue": 8,
    "genres": [
      "Action",
      "Adventure",
      "Drama",
      "War",
      "Western"
    ],
    "releaseSequence": "1956-09-01tt0048983"
  },
  {
    "imdbId": "tt0038675",
    "title": "Crisis",
    "year": "1946",
    "sortTitle": "Crisis (1946)",
    "slug": "crisis-1946",
    "grade": "B-",
    "gradeValue": 8,
    "genres": [
      "Drama",
      "Romance"
    ],
    "releaseSequence": "1946-02-25tt0038675"
  },
  {
    "imdbId": "tt0029754",
    "title": "West of Shanghai",
    "year": "1937",
    "sortTitle": "West of Shanghai (1937)",
    "slug": "west-of-shanghai-1937",
    "grade": "B",
    "gradeValue": 9,
    "genres": [
      "Adventure",
      "Drama",
      "War"
    ],
    "releaseSequence": "1937-10-28tt0029754"
  },
  {
    "imdbId": "tt0023694",
    "title": "White Zombie",
    "year": "1932",
    "sortTitle": "White Zombie (1932)",
    "slug": "white-zombie-1932",
    "grade": "B",
    "gradeValue": 9,
    "genres": [
      "Horror"
    ],
    "releaseSequence": "1932-07-28tt0023694"
  },
  {
    "imdbId": "tt0022321",
    "title": "The Road to Singapore",
    "year": "1931",
    "sortTitle": "Road to Singapore (1931)",
    "slug": "the-road-to-singapore-1931",
    "grade": "B-",
    "gradeValue": 8,
    "genres": [
      "Drama",
      "Romance"
    ],
    "releaseSequence": "1931-09-02tt0022321"
  },
  {
    "imdbId": "tt0021508",
    "title": "Up the River",
    "year": "1930",
    "sortTitle": "Up the River (1930)",
    "slug": "up-the-river-1930",
    "grade": "B-",
    "gradeValue": 8,
    "genres": [
      "Comedy",
      "Crime",
      "Drama"
    ],
    "releaseSequence": "1930-10-10tt0021508"
  }
]