{
  "imdbId": "tt0075784",
  "title": "A Bridge Too Far",
  "sortTitle": "bridge-too-far-1977",
  "releaseYear": "1977",
  "review": "a-bridge-too-far-1977",
  "grade": "C+",
  "reviewDate": "2008-12-03",
  "releaseDate": "1977-06-15",
  "genres": [
    "Drama",
    "History",
    "War"
  ],
  "countries": [
    "United States",
    "United Kingdom"
  ],
  "originalTitle": null,
  "runtimeMinutes": 175,
  "directorNames": [
    "Richard Attenborough"
  ],
  "writerNames": [
    "Cornelius Ryan",
    "William Goldman"
  ],
  "principalCastNames": [
    "Siem Vroom",
    "Marlies van Alcmaer",
    "Erik van 't Wout",
    "Wolfgang Preiss"
  ],
  "moreCastAndCrew": [
    {
      "name": "Sean Connery",
      "slug": "sean-connery",
      "creditKind": "performer",
      "titles": [
        "diamonds-are-forever-1971",
        "the-man-who-would-be-king-1975",
        "the-great-train-robbery-1978",
        "never-say-never-again-1983"
      ]
    },
    {
      "name": "Michael Caine",
      "slug": "michael-caine",
      "creditKind": "performer",
      "titles": [
        "the-man-who-would-be-king-1975",
        "the-eagle-has-landed-1976",
        "california-suite-1978",
        "dressed-to-kill-1980"
      ]
    },
    {
      "name": "Gene Hackman",
      "slug": "gene-hackman",
      "creditKind": "performer",
      "titles": [
        "the-poseidon-adventure-1972",
        "prime-cut-1972",
        "crimson-tide-1995",
        "the-royal-tenenbaums-2001"
      ]
    }
  ],
  "moreCollections": [],
  "moreReviews": [
    "the-brides-of-dracula-1960",
    "the-bridge-on-the-river-kwai-1957",
    "the-bridges-at-toko-ri-1954",
    "the-brigand-of-kandahar-1965"
  ]
}