{
  "imdbId": "tt0100436",
  "title": "Pump Up the Volume",
  "sortTitle": "pump-up-the-volume-1990",
  "releaseYear": "1990",
  "review": "pump-up-the-volume-1990",
  "grade": "B+",
  "reviewDate": "2026-05-01",
  "releaseDate": "1990-08-22",
  "genres": [
    "Comedy",
    "Drama",
    "Music"
  ],
  "countries": [
    "Canada",
    "United States"
  ],
  "originalTitle": null,
  "runtimeMinutes": 102,
  "reviewSequence": "2026-05-01-01",
  "directorNames": [
    "Allan Moyle"
  ],
  "writerNames": [
    "Allan Moyle"
  ],
  "principalCastNames": [
    "Anthony Luke Lucero",
    "Andy Romano",
    "Keith Stuart Thayer",
    "Cheryl Pollak"
  ],
  "moreCastAndCrew": [],
  "moreCollections": [],
  "moreReviews": [
    "the-public-defender-1931",
    "pulp-1972",
    "pumpkin-2002",
    "the-punisher-2004"
  ],
  "viewings": [
    "2026-05-01-01"
  ]
}