{
  "imdbId": "tt0044811",
  "title": "Secrets of Women",
  "sortTitle": "secrets-of-women-1952",
  "releaseYear": "1952",
  "review": "secrets-of-women-1952",
  "grade": "C-",
  "reviewDate": "2021-04-01",
  "releaseDate": "1952-11-03",
  "genres": [
    "Comedy",
    "Drama"
  ],
  "countries": [
    "Sweden"
  ],
  "originalTitle": "Kvinnors v\u00e4ntan",
  "runtimeMinutes": 107,
  "reviewSequence": "2021-04-01-01",
  "directorNames": [
    "Ingmar Bergman"
  ],
  "writerNames": [
    "Ingmar Bergman",
    "Gun Grut"
  ],
  "principalCastNames": [
    "Anita Bj\u00f6rk",
    "Eva Dahlbeck",
    "Maj-Britt Nilsson",
    "Birger Malmsten"
  ],
  "moreCastAndCrew": [
    {
      "name": "Ingmar Bergman",
      "slug": "ingmar-bergman",
      "creditKind": "director",
      "titles": [
        "to-joy-1950",
        "summer-interlude-1951",
        "sawdust-and-tinsel-1953",
        "summer-with-monika-1953"
      ]
    }
  ],
  "moreCollections": [],
  "moreReviews": [
    "the-secret-life-of-walter-mitty-1947",
    "the-secret-world-of-arrietty-2010",
    "the-sect-1991",
    "seed-of-chucky-2004"
  ]
}