{
  "imdbId": "tt0054416",
  "title": "The Two Faces of Dr. Jekyll",
  "sortTitle": "two-faces-of-dr-jekyll-1960",
  "releaseYear": "1960",
  "review": "the-two-faces-of-dr-jekyll-1960",
  "grade": "C",
  "reviewDate": "2025-11-25",
  "releaseDate": "1960-08-18",
  "genres": [
    "Horror"
  ],
  "countries": [
    "United Kingdom"
  ],
  "originalTitle": null,
  "runtimeMinutes": 88,
  "reviewSequence": "2025-11-25-01",
  "directorNames": [
    "Terence Fisher"
  ],
  "writerNames": [
    "Wolf Mankowitz",
    "Robert Louis Stevenson"
  ],
  "principalCastNames": [
    "Paul Massie",
    "Dawn Addams",
    "Christopher Lee",
    "David Kossoff"
  ],
  "moreCastAndCrew": [
    {
      "name": "Terence Fisher",
      "slug": "terence-fisher",
      "creditKind": "director",
      "titles": [
        "the-stranglers-of-bombay-1959",
        "sword-of-sherwood-forest-1960",
        "the-curse-of-the-werewolf-1961",
        "the-phantom-of-the-opera-1962"
      ]
    },
    {
      "name": "Christopher Lee",
      "slug": "christopher-lee",
      "creditKind": "performer",
      "titles": [
        "the-mummy-1959",
        "the-city-of-the-dead-1960",
        "scream-of-fear-1961",
        "the-terror-of-the-tongs-1961"
      ]
    }
  ],
  "moreCollections": [
    {
      "name": "Hammer Films",
      "slug": "hammer-films",
      "titles": [
        "the-stranglers-of-bombay-1959",
        "sword-of-sherwood-forest-1960",
        "the-curse-of-the-werewolf-1961",
        "stop-me-before-i-kill-1960"
      ]
    }
  ],
  "moreReviews": [
    "two-against-the-world-1936",
    "two-evil-eyes-1990",
    "two-fisted-law-1932",
    "two-for-the-seesaw-1962"
  ],
  "viewings": [
    "2025-11-25-01"
  ]
}