{
  "imdbId": "tt0074749",
  "title": "The Killing of a Chinese Bookie",
  "sortTitle": "killing-of-a-chinese-bookie-1976",
  "releaseYear": "1976",
  "review": "the-killing-of-a-chinese-bookie-1976",
  "grade": "C+",
  "reviewDate": "2008-12-26",
  "releaseDate": "1976-02-15",
  "genres": [
    "Crime",
    "Drama",
    "Thriller"
  ],
  "countries": [
    "United States"
  ],
  "originalTitle": null,
  "runtimeMinutes": 135,
  "reviewSequence": "2008-12-26-03",
  "directorNames": [
    "John Cassavetes"
  ],
  "writerNames": [
    "John Cassavetes"
  ],
  "principalCastNames": [
    "Ben Gazzara",
    "Timothy Carey",
    "Seymour Cassel",
    "Robert Phillips"
  ],
  "moreCastAndCrew": [],
  "moreCollections": [],
  "moreReviews": [
    "killers-kiss-1955",
    "the-killing-1956",
    "king-of-the-underworld-1939",
    "king-rat-1965"
  ]
}