{
  "imdbId": "tt0038854",
  "title": "The Postman Always Rings Twice",
  "sortTitle": "postman-always-rings-twice-1946",
  "releaseYear": "1946",
  "review": "the-postman-always-rings-twice-1946",
  "grade": "D+",
  "reviewDate": "2022-08-17",
  "releaseDate": "1946-04-30",
  "genres": [
    "Crime",
    "Drama",
    "Film-Noir",
    "Mystery",
    "Romance",
    "Thriller"
  ],
  "countries": [
    "United States"
  ],
  "originalTitle": null,
  "runtimeMinutes": 113,
  "directorNames": [
    "Tay Garnett"
  ],
  "writerNames": [
    "Harry Ruskin",
    "Niven Busch",
    "James M. Cain"
  ],
  "principalCastNames": [
    "Lana Turner",
    "John Garfield",
    "Cecil Kellaway",
    "Hume Cronyn"
  ],
  "moreCastAndCrew": [],
  "moreCollections": [],
  "moreReviews": [
    "possession-1981",
    "possessor-2020",
    "the-postman-always-rings-twice-1981",
    "pot-o-gold-1941"
  ]
}