{
  "imdbId": "tt0450345",
  "title": "The Wicker Man",
  "sortTitle": "wicker-man-2006",
  "releaseYear": "2006",
  "review": "the-wicker-man-2006",
  "grade": "D+",
  "reviewDate": "2025-10-17",
  "releaseDate": "2006-08-17",
  "genres": [
    "Horror",
    "Mystery",
    "Thriller"
  ],
  "countries": [
    "United States",
    "Mexico",
    "Canada",
    "Germany",
    "United Kingdom"
  ],
  "originalTitle": null,
  "runtimeMinutes": 102,
  "reviewSequence": "2025-10-17-01",
  "directorNames": [
    "Neil LaBute"
  ],
  "writerNames": [
    "Neil LaBute",
    "Anthony Shaffer"
  ],
  "principalCastNames": [
    "Nicolas Cage",
    "Ellen Burstyn",
    "Kate Beahan",
    "Frances Conroy"
  ],
  "moreCastAndCrew": [
    {
      "name": "Anthony Shaffer",
      "slug": "anthony-shaffer",
      "creditKind": "writer",
      "titles": [
        "frenzy-1972",
        "sleuth-1972",
        "the-wicker-man-1973",
        "death-on-the-nile-1978"
      ]
    }
  ],
  "moreCollections": [],
  "moreReviews": [
    "wicked-wicked-1973",
    "the-wicker-man-1973",
    "the-wild-angels-1966",
    "wild-at-heart-1990"
  ]
}