{
  "imdbId": "tt0404802",
  "title": "The Notorious Bettie Page",
  "sortTitle": "notorious-bettie-page-2005",
  "releaseYear": "2005",
  "review": "the-notorious-bettie-page-2005",
  "grade": "D",
  "reviewDate": "2007-08-16",
  "releaseDate": "2005-11-07",
  "genres": [
    "Biography",
    "Drama"
  ],
  "countries": [
    "United States"
  ],
  "originalTitle": null,
  "runtimeMinutes": 91,
  "reviewSequence": "2007-08-16-02",
  "directorNames": [
    "Mary Harron"
  ],
  "writerNames": [
    "Mary Harron",
    "Guinevere Turner"
  ],
  "principalCastNames": [
    "John Hans Tester",
    "Gretchen Mol",
    "Chris Bauer",
    "Jared Harris"
  ],
  "moreCastAndCrew": [],
  "moreCollections": [],
  "moreReviews": [
    "north-by-northwest-1959",
    "notorious-1946",
    "novocaine-2001",
    "now-voyager-1942"
  ],
  "viewings": [
    "2007-08-16-02"
  ]
}