{
  "imdbId": "tt0057682",
  "title": "Who's Been Sleeping in My Bed?",
  "sortTitle": "whos-been-sleeping-in-my-bed-1963",
  "releaseYear": "1963",
  "review": "whos-been-sleeping-in-my-bed-1963",
  "grade": "D",
  "reviewDate": "2009-05-11",
  "releaseDate": "1963-12-25",
  "genres": [
    "Comedy"
  ],
  "countries": [
    "United States"
  ],
  "originalTitle": null,
  "runtimeMinutes": 103,
  "reviewSequence": "2009-05-11-01",
  "directorNames": [
    "Daniel Mann"
  ],
  "writerNames": [
    "Jack Rose"
  ],
  "principalCastNames": [
    "Dean Martin",
    "Elizabeth Montgomery",
    "Martin Balsam",
    "Jill St. John"
  ],
  "moreCastAndCrew": [
    {
      "name": "Dean Martin",
      "slug": "dean-martin",
      "creditKind": "performer",
      "titles": [
        "sergeants-3-1962",
        "4-for-texas-1963",
        "kiss-me-stupid-1964",
        "robin-and-the-7-hoods-1964"
      ]
    }
  ],
  "moreCollections": [],
  "moreReviews": [
    "who-was-that-lady-1960",
    "the-whole-towns-talking-1935",
    "wicked-wicked-1973",
    "the-wicker-man-1973"
  ]
}